odoo/addons/cooperator_account_banking_mandate/__init__.py
odoo/addons/cooperator_account_banking_mandate/__manifest__.py
odoo/addons/cooperator_account_banking_mandate/models/__init__.py
odoo/addons/cooperator_account_banking_mandate/models/subscription_request.py
odoo/addons/cooperator_account_banking_mandate/views/subscription_request_views.xml
odoo14_addon_cooperator_account_banking_mandate-14.0.1.1.2.dist-info/METADATA
odoo14_addon_cooperator_account_banking_mandate-14.0.1.1.2.dist-info/WHEEL
odoo14_addon_cooperator_account_banking_mandate-14.0.1.1.2.dist-info/top_level.txt
odoo14_addon_cooperator_account_banking_mandate-14.0.1.1.2.dist-info/RECORD
