Metadata-Version: 2.1
Name: odoo14-addon-cooperator-account-banking-mandate
Version: 14.0.1.1.2
Summary: This module adds mandate selection to cooperator subscription request.
Home-page: https://coopdevs.org
Author: Som IT Cooperatiu SCCL
License: AGPL-3
Classifier: Programming Language :: Python
Classifier: Framework :: Odoo
Classifier: Framework :: Odoo :: 14.0
Classifier: License :: OSI Approved :: GNU Affero General Public License v3
Requires-Python: >=3.6
Requires-Dist: odoo14-addon-account-banking-mandate ==14.0.1.2.0
Requires-Dist: odoo14-addon-account-banking-sepa-direct-debit ==14.0.1.3.3
Requires-Dist: odoo14-addon-cooperator >=14.0.2.1.1
Requires-Dist: odoo <14.1dev,>=14.0a
